{"_id": "022-f1", "room-id": ["022-001", "022-027", "022-030", "022-031"], "room-name": ["G001 ", "G001 ", "G102 ", "G112 "]}
{"_id": "022-f2", "room-id": ["022-002", "022-004", "022-005", "022-026"], "room-name": ["G002 ", "G203 ", "G216 ", "G002 "]}
{"_id": "022-f3", "room-id": ["022-003"], "room-name": ["G003 "]}
{"_id": "022-f4", "room-id": ["022-020", "022-021", "022-028"], "room-name": ["yG409 ", "yG416 ", "G420 "]}
{"_id": "022-f5", "room-id": ["022-006", "022-007", "022-008", "022-009", "022-010", "022-029"], "room-name": ["G506 ", "MG516 ", "MG519 ", "WG510 ", "WG529 ", "G501 "]}
{"_id": "022-f7", "room-id": ["022-011", "022-012", "022-013", "022-014", "022-015", "022-016", "022-017", "022-018", "022-019", "022-022", "022-023", "022-024", "022-025"], "room-name": ["WG701 ", "WG708 ", "WG709 ", "WG712 ", "WG713 ", "WG718 ", "WG719 ", "WG725 ", "ZG702 ", "G715 ", "G709 ", "G712 ", "G704 "]}
